liquiclient/__init__.py
liquiclient/ck_client.py
liquiclient/config.py
liquiclient/es_client.py
liquiclient/kafka_client.py
liquiclient/mongo_client.py
liquiclient/mysql_client.py
liquiclient/redis_client.py
liquisource-1.2.19.dist-info/METADATA
liquisource-1.2.19.dist-info/WHEEL
liquisource-1.2.19.dist-info/top_level.txt
liquisource-1.2.19.dist-info/RECORD
