Metadata-Version: 2.4
Name: liquisource
Version: 1.2.19
Summary: A liquibase datasource client for python
Author-email: jiyis <425995717@qq.com>
Project-URL: Homepage, https://github.com/jiyis/liquisource
Project-URL: Bug Tracker, https://github.com/jiyis/liquisource/issues
Classifier: Programming Language :: Python :: 3
Classifier: License :: OSI Approved :: MIT License
Classifier: Operating System :: OS Independent
Requires-Python: >=3.7
Requires-Dist: clickhouse_connect==0.5.25
Requires-Dist: jproperties==2.1.1
Requires-Dist: pymongo==4.3.3
Requires-Dist: numpy==1.24.3
Requires-Dist: mysql-connector-python==8.0.33
Requires-Dist: redis==4.5.5
Requires-Dist: elasticsearch==7.10.1
Requires-Dist: confluent-kafka==2.5.3
